datasette_copy_to_memory/__init__.py
datasette_copy_to_memory-0.2.dist-info/LICENSE
datasette_copy_to_memory-0.2.dist-info/METADATA
datasette_copy_to_memory-0.2.dist-info/WHEEL
datasette_copy_to_memory-0.2.dist-info/entry_points.txt
datasette_copy_to_memory-0.2.dist-info/top_level.txt
datasette_copy_to_memory-0.2.dist-info/RECORD
