Metadata-Version: 2.1
Name: datasette-copy-to-memory
Version: 0.2
Summary: Copy database files into an in-memory database on startup
Home-page: https://github.com/simonw/datasette-copy-to-memory
Author: Simon Willison
License: Apache License, Version 2.0
Project-URL: Issues, https://github.com/simonw/datasette-copy-to-memory/issues
Project-URL: CI, https://github.com/simonw/datasette-copy-to-memory/actions
Project-URL: Changelog, https://github.com/simonw/datasette-copy-to-memory/releases
Platform: UNKNOWN
Classifier: Framework :: Datasette
Classifier: License :: OSI Approved :: Apache Software License
Requires-Python: >=3.7
License-File: LICENSE
Requires-Dist: datasette
Provides-Extra: test
Requires-Dist: pytest ; extra == 'test'
Requires-Dist: pytest-asyncio ; extra == 'test'
Requires-Dist: sqlite-utils ; extra == 'test'
